airflow/providers/common/io/LICENSE
airflow/providers/common/io/__init__.py
airflow/providers/common/io/get_provider_info.py
airflow/providers/common/io/operators/__init__.py
airflow/providers/common/io/operators/file_transfer.py
apache_airflow_providers_common_io-1.1.0.dist-info/entry_points.txt
apache_airflow_providers_common_io-1.1.0.dist-info/WHEEL
apache_airflow_providers_common_io-1.1.0.dist-info/METADATA
apache_airflow_providers_common_io-1.1.0.dist-info/RECORD
